discord/ext/pages/__init__.py
discord_ext_pages-0.0.1.dist-info/METADATA
discord_ext_pages-0.0.1.dist-info/WHEEL
discord_ext_pages-0.0.1.dist-info/RECORD
